LICENSE
impartial/__init__.py
impartial/impartial.py
impartial-0.2.0.dist-info/LICENSE
impartial-0.2.0.dist-info/WHEEL
impartial-0.2.0.dist-info/METADATA
impartial-0.2.0.dist-info/RECORD
