Metadata-Version: 2.1
Name: impartial
Version: 0.2.0
Summary: A lightweight extension of functools.partial
Home-page: https://github.com/georg-wolflein/impartial
License: Apache-2.0
Author: Georg Wölflein
Author-email: georgw7777@gmail.com
Requires-Python: >=3.7,<4.0
Classifier: Intended Audience :: Developers
Classifier: License :: OSI Approved :: Apache Software License
Classifier: Operating System :: OS Independent
Classifier: Programming Language :: Python :: 3
Classifier: Programming Language :: Python :: 3.7
Classifier: Programming Language :: Python :: 3.8
Classifier: Programming Language :: Python :: 3.9
Requires-Dist: typing-extensions (>=4.0.1,<5.0.0)
Project-URL: Repository, https://github.com/georg-wolflein/impartial
